{"images":[{"startdate":"20240523","fullstartdate":"202405230700","enddate":"20240524","url":"/th?id=OHR.IndianStarTortoise_EN-US4160827746_1920x1080.jpg&rf=LaDigue_1920x1080.jpg&pid=hp","urlbase":"/th?id=OHR.IndianStarTortoise_EN-US4160827746","copyright":"Indian star tortoise, Sri Lanka (© Robin Chittenden/Minden Pictures)","copyrightlink":"https://www.bing.com/search?q=World+Turtle+Day&form=hpcapt&filters=HpDate%3a%2220240523_0700%22","title":"Looking for a shell-ter","quiz":"/search?q=Bing+homepage+quiz&filters=WQOskey:%22HPQuiz_20240523_IndianStarTortoise%22&FORM=HPQUIZ","wp":true,"hsh":"abfc8a1ec86f4b56bcd9afab4def1175","drk":1,"top":1,"bot":1,"hs":[]}],"tooltips":{"loading":"Loading...","previous":"Previous image","next":"Next image","walle":"This image is not available to download as wallpaper.","walls":"Download this image. Use of this image is restricted to wallpaper only."}}